ow2_cache_merge/__init__.py
ow2_cache_merge/config.toml
ow2_cache_merge/main.py
ow2_cache_merge/lib/__init__.py
ow2_cache_merge/lib/dxvk-cache-tool
ow2_cache_merge-1.0.1.dist-info/LICENSE
ow2_cache_merge-1.0.1.dist-info/METADATA
ow2_cache_merge-1.0.1.dist-info/WHEEL
ow2_cache_merge-1.0.1.dist-info/entry_points.txt
ow2_cache_merge-1.0.1.dist-info/top_level.txt
ow2_cache_merge-1.0.1.dist-info/RECORD
