Metadata-Version: 2.1
Name: ow2-cache-merge
Version: 1.0.1
Summary: A tool for downloading and merging multiple Overwatch 2 dxvk cache files
Home-page: https://github.com/leventguney/ow2-cache-merge
Author: Levent Guney
Author-email: dtleventmobile@gmail.com
License: MIT
Keywords: Overwatch2,Overwatch,dxvk,cache,merge
License-File: LICENSE
Requires-Dist: loguru
Requires-Dist: toml
